Verilog/primes/primes.v
module primes (
    
    input wire [3:0] x, // input data (4 bits)
    output reg z        // output. 0-no prime, 1-prime
    );

    /* We use a procedural description for the circuit */
    always @* begin
        /* With the 'case' sentence we can execute a different operation
         * depending on the value of a variable or expression. In our case,
         * it is specially convenient since the output only depends on "x".*/
        case(x)         /* expression to test */
        2:  z = 1;      /* action in case the value is "2" */
        3:  z = 1;      /* etc. */
        5:  z = 1;
        7:  z = 1;
        11: z = 1;
        13: z = 1;
        default: z = 0; /* action in any other case
                         * Note that a combinational circuit should always
                         * generate an output value for any input value, so
                         * the 'default' is necessary in most cases when a
                         * 'case' statement to describe combinational
                         * behavior. */
        endcase
    end

endmodule

Verilog/primes/primes_tb.v
// Design:      primes
// File:        primes.v
// Description: Prime number detector
// Author:       Jorge Juan-Chico <jjchico@gmail.com>
// Date:        09/11/2018 (initial version)

/*
   Lesson 3.2: 4-bit prime number detector.

   This file contains a test bench for module 'primes'.
*/

`timescale 1ns / 1ps

// Base time to easy test pattern specification
`define BTIME 10

module test ();

    // Input
    /* The signal that generates the inputs to our circuit is a 4-bit 
     * variable. */
    reg [3:0] x;

    // Outputs
    wire z;

    // UUT instance
    /* Multi-bit signals are connected like bit signals */
    primes uut (.x(x), .z(z));

    /* The 'initial' process below initializes the test patterns and includes
       the simulation directives. */
    initial begin
        // Input initialization
        x = 4'b0000;
        /* 'x' is initialized to zero by using the zero value in binary
           indicating explicitly that it is a 4-bit signal. The complete 
           format for literal numbers in Verilog is:
         *   <number of bits>'<base><value>
         * where <base> may be, among others:
         *   b: binary
         *   o: octal
         *   h: hexadecimal
         *   d: decimal
         * If <base> is omitted, it is considered decimal. If the number of
         * bits is omitted, the value includes at least 32 bits, but it is 
         * automatically extended if necessary to complete the operations.
         * In general, if the number of bits is known in advance, it is
         * recommended to make it explicit in constants.
         * Alternatively, 'x' could have been initialized like:
         *   x = 4'h00      // hexadecimal
         *   x = 'b0000     // binary, number of bits omitted
         *   x = 0          // base and number of bits omitted. It is assumed
         *                  // a decimal zero with enough bits to assign all
         *                  // the bit of 'x' to zero.
         */

        // Waveform generation
        $dumpfile("primes_tb.vcd");
        $dumpvars(0,test);

        // Text output generation
        /* In this design, the text output is very convenient because it is
         * faster and easier to check than by looking at the detailed signal
         * waveforms. */
        $display("x   z");          // header
        $display("-----");
        $monitor("%d  %b", x, z);

        // Simulation ends
        /* Simulation end time is programmed as a function of 'BTIME'. The
         * value 16*`BTIME is enough for the inputs to go through all possible
         * values. */
        #(16*`BTIME) $finish;
    end

    // Input test pattern generation
    /* To make the input signal to go through all possible values we just 
     * increment 'x' every `BTIME nanoseconds. Multi-bit variables can be
     * used as regular integer variables and can be opperated with arithmetic
     * operators as expected. */
    always
        #(`BTIME) x = x + 1;

endmodule // test

Verilog/primes/primes_tb.vcd
$date
	Mon Aug  8 22:30:59 2022
$end
$version
	Icarus Verilog
$end
$timescale
	1ps
$end
$scope module test $end
$var wire 1 ! z $end
$var reg 4 " x [3:0] $end
$scope module uut $end
$var wire 4 # x [3:0] $end
$var reg 1 ! z $end
$upscope $end
$upscope $end
$enddefinitions $end
#0
$dumpvars
b0 #
b0 "
0!
$end
#10000
b1 "
b1 #
#20000
1!
b10 "
b10 #
#30000
b11 "
b11 #
#40000
0!
b100 "
b100 #
#50000
1!
b101 "
b101 #
#60000
0!
b110 "
b110 #
#70000
1!
b111 "
b111 #
#80000
0!
b1000 "
b1000 #
#90000
b1001 "
b1001 #
#100000
b1010 "
b1010 #
#110000
1!
b1011 "
b1011 #
#120000
0!
b1100 "
b1100 #
#130000
1!
b1101 "
b1101 #
#140000
0!
b1110 "
b1110 #
#150000
b1111 "
b1111 #
#160000
b0 "
b0 #
