Verilog/latche/latches.v

`timescale 1ns / 1ps

//////////////////////////////////////////////////////////////////////////
// Asynchronous SR latch                                                //
//////////////////////////////////////////////////////////////////////////
/*
   This latch does not have a clock input. When input 's' is activated 
   (s = 1) the latch state changes to '1', and when the input 'r' is activated
   (r = 1), the state changes to '0'. The input s = r = 1 is not defined for 
   this latch so the value of the state is set to unknown ('x') in our 
   description so signal that a prohibited input combination has taken place.
 */

module sra(
    input wire s,   // set (set to '1')
    input wire r,   // reset (set to '0')
    output reg q    // state (stored value)
    /* Variables (type 'reg' in Verilog) are the only type of signal that
     * can keep a value if not assigned, so only vaiables can used to
     * model storage elements like latches. */
    );


    always @(s, r)
        case ({s, r})
        /* Variables representing memory elements should be assigned
         * with the non-blocking assignment operator '<=' instead of
         * the normal blocking assignment operator '='. With '<=', all
         * the right-side expressions in a block are evaluated first
         * and the actual assignments only happen at the end of the
         * block. This behavior models sequential circuits better. We will
         * see more about blocking and non-blocking assignments in 
         * lesson 6.3. */
        2'b01: q <= 1'b0;
        2'b10: q <= 1'b1;
        2'b11: q <= 1'bx;

        /* The latch behavior is derived from the fact that signal 'q'
         * is not always assigned even if the 'always' block is
         * activated. When 'q' is not assigned (s = r = 0) the value of
         * 'q' is kept as it is expected in a storage element. */
        endcase
endmodule // sra

//////////////////////////////////////////////////////////////////////////
// Gated SR latch. Ative-high clock.                                   //
//////////////////////////////////////////////////////////////////////////
/*
   This latch is "synchronous" because it is controlled by a clock signal
   ('clk'). The state of the latch can only be changed when clk = 1 (the clock
   is at a high level). In a similar way, active-low latches change their
   state only when clk = 0.
*/

module srg(
    input clk,      // clock signal
    input s,        // set (set to '1')
    input r,        // reset (set to '0')
    output reg q    // state (stored value)
    );

    always @(clk, s, r)
        if (clk == 1)
            case ({s, r})
            2'b01: q <= 1'b0;
            2'b10: q <= 1'b1;
            2'b11: q <= 1'bx;
            endcase
endmodule // srg


//////////////////////////////////////////////////////////////////////////
// Master-Slave SR latch                                                //
//////////////////////////////////////////////////////////////////////////
/*
   This latch it build by the chain connection of two gated latches controlled
   by opposite clock levels. When clk = 1, the first latch (master) loads
   the new state while the second latch (slave) retains the old state. When
   'clk' changes to '0' the master's state is locked and is transferred to
   the slave latch, thus changing the output of the device.
   
   The idea behind the M-S structure is make the output changes only possible 
   at the instant the clock goes from '1' to '0' (or '0' to '1' if the latches
   are active-low). Making the output changes only possible at very precise 
   instants (the negative edge of the clock in this case) is good to make
   circuitos more robust and deterministic. However, the next state of the 
   latch is still determined by the value of 's' and 'r' whenever the clock is
   active, like in a regular gated SR latch. */

module srms (
    input wire clk,
    input wire s,
    input wire r,
    output wire q
    );

    srg master(.clk(clk), .s(s), .r(r), .q(qm));
    /* The slave inputs are connected in a way that the slave will copy
     * the state of the master. */
    srg slave(.clk(clk_neg), .s(qm), .r(qm_neg), .q(q));

    /* We now generate the negated output of the master and the
     * negated clock signal. */
    assign qm_neg = ~qm;
    assign clk_neg = ~clk;

endmodule // srms


//////////////////////////////////////////////////////////////////////////
// Edge-triggered SR latch (SR flip-flop)                               //
//////////////////////////////////////////////////////////////////////////
/*
   Edge-triggered latches (AKA flip-flops) only change their states and
   evaluate their input control signals at the clock edge, either positive
   (0 to 1) or negative (1 to 0). The provide the best control of the state
   change compared to other latches so they are the preferred choice when 
   designing sequential circuits.
*/

module srff (
    input wire clk, // clock signal
    input wire s,   // set (set to '1')
    input wire r,   // reset (set to '0')
    output reg q    // state (stored value)
    );

    /* Edge-triggered conditions are indicated by 'posedge' and 'negedge'
     * keywords in the process sensitivity list. In this case, the process
     * is only evaluated when 'clk' changes from 1 to 0 (negative edge) so
     * inputs 's' and 'r' are only evaluated and the state stored in 'q'
     * can only change at that time. */
    always @(negedge clk)
        case ({s, r})
        2'b01: q <= 1'b0;
        2'b10: q <= 1'b1;
        2'b11: q <= 1'bx;
        endcase
endmodule // srff

Verilog/latche/latches_tb.v
`timescale 1ns / 1ps

// Test bench

module test ();

    reg clk = 0;            // clock
    reg s = 0;              // set
    reg r = 0;              // reset
    wire qa, qg, qms, qff;  // latch outputs

    // Latch instantiation
    /* Asynchronous latch */
    sra uut_sra(.s(s), .r(r), .q(qa));
    /* Gated latch */
    srg uut_srg(.clk(clk), .s(s), .r(r), .q(qg));
    /* Master-Slave latch */
    srms uut_srms(.clk(clk), .s(s), .r(r), .q(qms));
    /* Edge-triggered latch (flip-flop) */
    srff uut_srff(.clk(clk), .s(s), .r(r), .q(qff));

    // Simulation output and control
    initial	begin
        // Waveform generation
        $dumpfile("latches_tb.vcd");
        $dumpvars(0, test);

        // Text output
        $display("      time  clk s r   qa  qg  qms qff");
        $monitor("%d  %b   %b %b   %b   %b   %b   %b",
                   $stime, clk, s, r, qa, qg, qms, qff);

        // Control inputs
        /* 's' and 'r' are changed to produce state changes in
         * various conditions. Delays are relative to the previous
         * assignments. Absolute times are shown as comments. */
        #8  r = 1;    // t = 8
        #17 r = 0;    // t = 25
        #9  s = 1;    // t = 34
        #2  s = 0;    // t = 36
        #8  r = 1;    // t = 44
        #2  r = 0;    // t = 46
        #6  s = 1;    // t = 52

        // Simulation ends
        #20 $finish;
    end

    // Periodic clock signal (20ns period)
    always
        #10 clk = ~clk;

endmodule

Verilog/latche/latches_tb.vcd
$date
	Fri Aug 12 17:53:02 2022
$end
$version
	Icarus Verilog
$end
$timescale
	1ps
$end
$scope module test $end
$var wire 1 ! qms $end
$var wire 1 " qg $end
$var wire 1 # qff $end
$var wire 1 $ qa $end
$var reg 1 % clk $end
$var reg 1 & r $end
$var reg 1 ' s $end
$scope module uut_sra $end
$var wire 1 & r $end
$var wire 1 ' s $end
$var reg 1 $ q $end
$upscope $end
$scope module uut_srff $end
$var wire 1 % clk $end
$var wire 1 & r $end
$var wire 1 ' s $end
$var reg 1 # q $end
$upscope $end
$scope module uut_srg $end
$var wire 1 % clk $end
$var wire 1 & r $end
$var wire 1 ' s $end
$var reg 1 " q $end
$upscope $end
$scope module uut_srms $end
$var wire 1 % clk $end
$var wire 1 ( clk_neg $end
$var wire 1 ) qm_neg $end
$var wire 1 & r $end
$var wire 1 ' s $end
$var wire 1 * qm $end
$var wire 1 ! q $end
$scope module master $end
$var wire 1 % clk $end
$var wire 1 & r $end
$var wire 1 ' s $end
$var reg 1 * q $end
$upscope $end
$scope module slave $end
$var wire 1 ( clk $end
$var wire 1 ) r $end
$var wire 1 * s $end
$var reg 1 ! q $end
$upscope $end
$upscope $end
$upscope $end
$enddefinitions $end
#0
$dumpvars
x*
x)
1(
0'
0&
0%
x$
x#
x"
x!
$end
#8000
0$
1&
#10000
1)
0*
0"
0(
1%
#20000
0!
0#
1(
0%
#25000
0&
#30000
0(
1%
#34000
0)
1$
1*
1"
1'
#36000
0'
#40000
1!
1(
0%
#44000
0$
1&
#46000
0&
#50000
0(
1%
#52000
1$
1'
#60000
1#
1(
0%
